webrtc_audio/__init__.py
webrtc_audio/hello.cpython-38-darwin.so
webrtc_audio-0.0.1.dist-info/METADATA
webrtc_audio-0.0.1.dist-info/WHEEL
webrtc_audio-0.0.1.dist-info/top_level.txt
webrtc_audio-0.0.1.dist-info/RECORD
