Metadata-Version: 2.1
Name: webrtc-audio
Version: 0.0.1
Summary: Cython Bindings for WebRTC Audio Library
Home-page: https://github.com/spokestack/webrtc-audio
Author: Spokestack
Author-email: support@spokestack.io
License: UNKNOWN
Platform: UNKNOWN
Classifier: Programming Language :: Python :: 3
Classifier: License :: OSI Approved :: Apache Software License
Classifier: Operating System :: OS Independent
Requires-Python: >=3.8
Requires-Dist: numpy
Requires-Dist: Cython
